fa6_icons/__init__.py
fa6_icons/_modidx.py
fa6_icons/core.py
fa6_icons/icons.py
fa6_icons-0.0.3.dist-info/licenses/LICENSE
fa6_icons-0.0.3.dist-info/METADATA
fa6_icons-0.0.3.dist-info/WHEEL
fa6_icons-0.0.3.dist-info/entry_points.txt
fa6_icons-0.0.3.dist-info/top_level.txt
fa6_icons-0.0.3.dist-info/RECORD
